mydot/__init__.py
mydot/__main__.py
mydot/actions.py
mydot/clip.py
mydot/console.py
mydot/editor.py
mydot/exceptions.py
mydot/logging.py
mydot/repository.py
mydot-0.8.0.dist-info/licenses/LICENSE.md
mydot-0.8.0.dist-info/METADATA
mydot-0.8.0.dist-info/WHEEL
mydot-0.8.0.dist-info/entry_points.txt
mydot-0.8.0.dist-info/top_level.txt
mydot-0.8.0.dist-info/RECORD
