Metadata-Version: 2.4
Name: mydot
Version: 0.8.0
Summary: Manage and edit $HOME dotfiles using Python + git = <3
Home-page: https://github.com/gikeymarcia/mydot
Author: Mikey Garcia
Author-email: gikeymarcia@gmail.com
License: GPL-3.0
License-File: LICENSE.md
Requires-Dist: pydymenu>=0.5.0
Requires-Dist: rich
Dynamic: author
Dynamic: author-email
Dynamic: description
Dynamic: description-content-type
Dynamic: home-page
Dynamic: license
Dynamic: license-file
Dynamic: requires-dist
Dynamic: summary
